{
  "tr": [
    {
      "title": "KAROTLU SONDAJ EKİPMANLARI",
      "description": "Madenciliğe dair tüm ekipmanmların imalat ve satışı, karotlu sondaj ekipmanları ve kaya delici ekipmanları.",
      "cta_button": "Detaylı Bilgi",
      "cta_link": "/hizmetler/karotlu"
    },
    {
      "title": "RTD GRUBU ",
      "description": "Madenciliğe dair tüm ekipmanmların imalat ve satışı, karotlu sondaj eki̇pmanları ve kaya delici eki̇pmanları.",
      "cta_button": "Detayli Bilgi",
      "cta_link": "/hizmetler/rdt"
    }
  ],
  "en": [
    {
      "title": "CORED SERVICES",
      "description": "Manufacturing and sales of all mining equipment, core drilling equipment and rock drilling equipment.",
      "cta_button": "Learn more",
      "cta_link": "/services/cored"
    },
    {
      "title": "RTD SERVICES",
      "description": "Manufacturing and sales of all mining equipment, core drilling equipment and rock drilling equipment.",
      "cta_button": "Learn more",
      "cta_link": "/services/rdt"
    }
  ]
}